pyile_protocol/__init__.py
pyile_protocol/lib/__init__.py
pyile_protocol/lib/error.py
pyile_protocol/lib/utils.py
pyile_protocol/lib/messenger/Messenger.py
pyile_protocol/lib/messenger/__init__.py
pyile_protocol/lib/peers/AuthPeer.py
pyile_protocol/lib/peers/JoinPeer.py
pyile_protocol/lib/peers/Peer.py
pyile_protocol/lib/peers/__init__.py
pyile_protocol/tests/__init__.py
pyile_protocol/tests/test_auth.py
pyile_protocol/tests/test_send_peer.py
pyile_protocol-0.1.0.dist-info/LICENSE
pyile_protocol-0.1.0.dist-info/METADATA
pyile_protocol-0.1.0.dist-info/WHEEL
pyile_protocol-0.1.0.dist-info/top_level.txt
pyile_protocol-0.1.0.dist-info/RECORD
