Metadata-Version: 2.1
Name: pyile-protocol
Version: 0.1.0
Summary: Protocol library for p2p messaging and authentication.
Home-page: https://github.com/nburnet1/pyile-protocol
Author: Noah Burnette
Author-email: nburnet1@duck.com
License: UNKNOWN
Platform: UNKNOWN
License-File: LICENSE
Requires-Dist: pyile-protocol
